oneview_client/__init__.py
oneview_client/auditing.py
oneview_client/client.py
oneview_client/exceptions.py
oneview_client/ilo_utils.py
oneview_client/managers.py
oneview_client/models.py
oneview_client/states.py
oneview_client/utils.py
oneview_client/tests/__init__.py
oneview_client/tests/fixtures.py
oneview_client/tests/functional/__init__.py
oneview_client/tests/functional/test_oneview_client.py
oneview_client/tests/unit/__init__.py
oneview_client/tests/unit/test_auditing.py
oneview_client/tests/unit/test_exceptions.py
oneview_client/tests/unit/test_ilo_utils.py
oneview_client/tests/unit/test_managers.py
oneview_client/tests/unit/test_models.py
oneview_client/tests/unit/test_oneview_client.py
oneview_client/tests/unit/test_utils.py
python_oneviewclient-2.6.6.dist-info/DESCRIPTION.rst
python_oneviewclient-2.6.6.dist-info/METADATA
python_oneviewclient-2.6.6.dist-info/RECORD
python_oneviewclient-2.6.6.dist-info/WHEEL
python_oneviewclient-2.6.6.dist-info/metadata.json
python_oneviewclient-2.6.6.dist-info/pbr.json
python_oneviewclient-2.6.6.dist-info/top_level.txt
