Metadata-Version: 2.0
Name: python-oneviewclient
Version: 2.6.6
Summary: Library to use OneView to provide nodes for Ironic
Home-page: http://www.openstack.org/
Author: OpenStack
Author-email: openstack-dev@lists.openstack.org
License: UNKNOWN
Platform: UNKNOWN
Classifier: Environment :: OpenStack
Classifier: Intended Audience :: Information Technology
Classifier: Intended Audience :: System Administrators
Classifier: License :: OSI Approved :: Apache Software License
Classifier: Operating System :: POSIX :: Linux
Classifier: Programming Language :: Python
Classifier: Programming Language :: Python :: 2
Classifier: Programming Language :: Python :: 2.7
Classifier: Programming Language :: Python :: 3
Classifier: Programming Language :: Python :: 3.4
Requires-Dist: Babel (!=2.4.0,>=2.3.4)
Requires-Dist: oslo.serialization (>=1.10.0)
Requires-Dist: pbr (>=2.0.0,!=2.1.0)
Requires-Dist: retrying (!=1.3.0,>=1.2.3)
Requires-Dist: six (>=1.9.0)
